splurge_sql_generator/__init__.py
splurge_sql_generator/__main__.py
splurge_sql_generator/cli.py
splurge_sql_generator/code_generator.py
splurge_sql_generator/config.py
splurge_sql_generator/exceptions.py
splurge_sql_generator/file_utils.py
splurge_sql_generator/schema_parser.py
splurge_sql_generator/sql_helper.py
splurge_sql_generator/sql_parser.py
splurge_sql_generator/type_definitions.py
splurge_sql_generator/utils.py
splurge_sql_generator/templates/python_class.j2
splurge_sql_generator-2025.5.0.dist-info/licenses/LICENSE
splurge_sql_generator-2025.5.0.dist-info/METADATA
splurge_sql_generator-2025.5.0.dist-info/WHEEL
splurge_sql_generator-2025.5.0.dist-info/entry_points.txt
splurge_sql_generator-2025.5.0.dist-info/top_level.txt
splurge_sql_generator-2025.5.0.dist-info/RECORD
