Metadata-Version: 2.4
Name: splurge-sql-generator
Version: 2025.5.0
Summary: A Python tool for generating Python classes from SQL files
Author: Jim Schilling
Maintainer: Jim Schilling
License-Expression: MIT
Project-URL: Homepage, https://github.com/jim-schilling/splurge-sql-generator
Project-URL: Repository, https://github.com/jim-schilling/splurge-sql-generator
Project-URL: Documentation, https://github.com/jim-schilling/splurge-sql-generator#readme
Project-URL: Issues, https://github.com/jim-schilling/splurge-sql-generator/issues
Project-URL: Changelog, https://github.com/jim-schilling/splurge-sql-generator/blob/main/CHANGELOG.md
Keywords: sql,code-generation,python,sqlalchemy,jinja2
Classifier: Development Status :: 4 - Beta
Classifier: Intended Audience :: Developers
Classifier: Operating System :: OS Independent
Classifier: Programming Language :: Python :: 3
Classifier: Programming Language :: Python :: 3.10
Classifier: Programming Language :: Python :: 3.11
Classifier: Programming Language :: Python :: 3.12
Classifier: Programming Language :: Python :: 3.13
Classifier: Programming Language :: Python :: 3 :: Only
Classifier: Topic :: Database
Classifier: Topic :: Software Development :: Code Generators
Classifier: Topic :: Software Development :: Libraries :: Python Modules
Requires-Python: >=3.10
License-File: LICENSE
Requires-Dist: sqlalchemy>=2.0.42
Requires-Dist: sqlparse>=0.5.3
Requires-Dist: jinja2>=3.1.0
Requires-Dist: PyYAML>=6.0.2
Requires-Dist: splurge-safe-io>=2025.1.1
Provides-Extra: dev
Requires-Dist: pytest>=8.4.1; extra == "dev"
Requires-Dist: pytest-cov>=6.2.1; extra == "dev"
Requires-Dist: pytest-xdist>=3.8.0; extra == "dev"
Requires-Dist: pytest-mock>=3.15.1; extra == "dev"
Requires-Dist: hypothesis>=6.97.4; extra == "dev"
Requires-Dist: mypy>=1.18.2; extra == "dev"
Requires-Dist: pre-commit>=4.3.0; extra == "dev"
Requires-Dist: ruff>=0.12.7; extra == "dev"
Provides-Extra: test
Requires-Dist: pytest>=8.4.1; extra == "test"
Requires-Dist: pytest-cov>=6.2.1; extra == "test"
Requires-Dist: hypothesis>=6.97.4; extra == "test"
Requires-Dist: pytest-xdist>=3.8.0; extra == "test"
Provides-Extra: lint
Requires-Dist: mypy>=1.18.2; extra == "lint"
Requires-Dist: ruff>=0.12.7; extra == "lint"
Dynamic: license-file
